autotest/__init__.py
autotest/__main__.py
autotest/plugin.py
autotest/webdriver.py
pytest_autotest-0.0.1.dist-info/METADATA
pytest_autotest-0.0.1.dist-info/WHEEL
pytest_autotest-0.0.1.dist-info/entry_points.txt
pytest_autotest-0.0.1.dist-info/top_level.txt
pytest_autotest-0.0.1.dist-info/RECORD
